{
	"configurations" : 
	[
		{
			"directories" : 
			[
				{
					"build" : ".",
					"hasInstallRule" : true,
					"minimumCMakeVersion" : 
					{
						"string" : "3.0"
					},
					"projectIndex" : 0,
					"source" : ".",
					"targetIndexes" : 
					[
						0,
						1
					]
				}
			],
			"name" : "Release",
			"projects" : 
			[
				{
					"directoryIndexes" : 
					[
						0
					],
					"name" : "fake6502",
					"targetIndexes" : 
					[
						0,
						1
					]
				}
			],
			"targets" : 
			[
				{
					"directoryIndex" : 0,
					"id" : "fake6502::@6890427a1f51a3e7e1df",
					"jsonFile" : "target-fake6502-Release-1ac1b55abafc44771d2d.json",
					"name" : "fake6502",
					"projectIndex" : 0
				},
				{
					"directoryIndex" : 0,
					"id" : "myne::@6890427a1f51a3e7e1df",
					"jsonFile" : "target-myne-Release-844127ddb1d39b266300.json",
					"name" : "myne",
					"projectIndex" : 0
				}
			]
		}
	],
	"kind" : "codemodel",
	"paths" : 
	{
		"build" : "/home/ayeka/projects/Fake6502/build",
		"source" : "/home/ayeka/projects/Fake6502"
	},
	"version" : 
	{
		"major" : 2,
		"minor" : 1
	}
}
